{
  "flow_type": "data_list",
  "flow_name": "onboarding_settings_pages",
  "status": "released",
  "data_list_name": "onboarding_settings_pages",
  "rows": [
    {
      "id": "page_1",
      "completed": false,
      "completed_count": 0
    },
    {
      "id": "page_2",
      "completed": false,
      "completed_count": 1
    },
    {
      "id": "page_3",
      "completed": false,
      "completed_count": 2
    },
    {
      "id": "page_4",
      "completed": false,
      "completed_count": 3
    },
    {
      "id": "page_5",
      "completed": false,
      "completed_count": 4
    }
  ],
  "_source": {
    "name": "kids_teens_pa",
    "path": "templates/PA onboarding templates.xlsx",
    "url": "https://docs.google.com/spreadsheets/d/1Efq1duWdtaioK0tVhxuFSfdeFO_wMQzs5aDyl6hQ7_0"
  },
  "_metadata": {
    "completed": {
      "type": "boolean"
    },
    "completed_count": {
      "type": "number"
    }
  }
}